{"Exif":{"Lat":0,"Long":0,"Date":"2015-03-21T10:44:22+08:00","Tags":{"ApertureValue":5.310704,"ColorSpace|int":"1","Contrast|int":"2","Copyright":"https://creativecommons.org/licenses/by-nc/2.0/","CustomRendered|int":"0","DateTimeDigitized|time.Time":"2015-03-21T10:44:22+08:00","DateTimeOriginal|time.Time":"2015-03-21T10:44:22+08:00","DateTime|time.Time":"2015-03-21T15:12:51+08:00","ExifIFDPointer|int":"360","ExifVersion":"0221","ExposureBiasValue":0.7,"ExposureMode|int":"1","ExposureProgram|int":"3","ExposureTime|*big.Rat":"1/125","FNumber":6.3,"Flash|int":"16","FocalLength":105,"FocalLengthIn35mmFilm|int":"157","ISOSpeedRatings|int":"800","ImageDescription":"https://www.flickr.com/photos/runnerwill/16857138496","LensModel":"Sigma Lens","Make":"RICOH IMAGING COMPANY, LTD.","MeteringMode|int":"2","Model":"PENTAX K-3","Orientation|int":"1","PixelXDimension|int":"6016","PixelYDimension|int":"4000","ResolutionUnit|int":"2","Saturation|int":"0","SceneCaptureType|int":"0","SensingMethod|int":"2","Sharpness|int":"2","ShutterSpeedValue":6.965784,"Software":"Adobe Photoshop Elements 10.0 Windows","SubjectDistanceRange|int":"1","ThumbJPEGInterchangeFormatLength|int":"9488","ThumbJPEGInterchangeFormat|int":"908","WhiteBalance|int":"0","XResolution":240,"YResolution":240}}}
