{"Exif":{"Lat":0,"Long":0,"Date":"2006-06-08T09:51:47+08:00","Tags":{"ApertureValue":5.310704,"Artist":"Jorge Royan; https://www.royan.com.ar/","ColorSpace|int":"65535","Copyright":"https://creativecommons.org/licenses/by-sa/3.0/","CustomRendered|int":"0","DateTimeDigitized|time.Time":"2010-04-25T09:40:17+08:00","DateTimeOriginal|time.Time":"2006-06-08T09:51:47+08:00","DateTime|time.Time":"2010-04-25T09:40:17+08:00","ExifIFDPointer|int":"440","ExifVersion":"0221","ExposureBiasValue":0,"ExposureMode|int":"0","ExposureProgram|int":"3","ExposureTime|*big.Rat":"1/20","FNumber":6.3,"Flash|int":"16","FocalLength":48,"FocalPlaneResolutionUnit|int":"2","FocalPlaneXResolution":3086.9257950530036,"FocalPlaneYResolution":3091.295116772824,"ISOSpeedRatings|int":"400","ImageDescription":"https://commons.wikimedia.org/wiki/File:Detail_of_a_1800%27s_small_sailboat_deck,_Auckland_-_1059.jpg","Make":"Canon","MaxApertureValue":3,"MeteringMode|int":"5","Model":"Canon EOS 5D","Orientation|int":"1","PixelXDimension|int":"4368","PixelYDimension|int":"2912","ResolutionUnit|int":"2","SceneCaptureType|int":"0","ShutterSpeedValue":4.321928,"Software":"Adobe Photoshop CS2 Macintosh","ThumbJPEGInterchangeFormatLength|int":"6686","ThumbJPEGInterchangeFormat|int":"940","WhiteBalance|int":"0","XResolution":240,"YResolution":240}}}
